fastapi_problem_details-0.1.4.dist-info/METADATA
fastapi_problem_details-0.1.4.dist-info/WHEEL
fastapi_problem_details-0.1.4.dist-info/entry_points.txt
fastapi_problem_details-0.1.4.dist-info/licenses/LICENSE
fastapi_problem_details/__init__.py
fastapi_problem_details/error_handlers.py
fastapi_problem_details/models.py
fastapi_problem_details/py.typed
fastapi_problem_details-0.1.4.dist-info/RECORD
