Metadata-Version: 2.1
Name: fastapi-problem-details
Version: 0.1.4
Summary: Structure your FastAPI APIs error responses with consistent and machine readable format using the RFC 9457 "Problem Details for HTTP APIs" standard
Keywords: fastapi,problem,plugin
Author-Email: g0di <benoit.godard.p@gmail.com>
License: MIT
Classifier: Development Status :: 5 - Production/Stable
Classifier: Environment :: Plugins
Classifier: Environment :: Web Environment
Classifier: Framework :: FastAPI
Classifier: Intended Audience :: Developers
Classifier: Intended Audience :: Information Technology
Classifier: Intended Audience :: Telecommunications Industry
Classifier: License :: OSI Approved :: MIT License
Classifier: Operating System :: OS Independent
Classifier: Programming Language :: Python :: 3 :: Only
Classifier: Programming Language :: Python :: 3.10
Classifier: Programming Language :: Python :: 3.11
Classifier: Programming Language :: Python :: 3.12
Classifier: Programming Language :: Python :: Implementation :: CPython
Classifier: Topic :: Internet
Classifier: Topic :: Internet :: WWW/HTTP
Classifier: Topic :: Internet :: WWW/HTTP :: HTTP Servers
Classifier: Topic :: Software Development :: Libraries
Project-URL: Homepage, https://github.com/g0di/fastapi-problem-details
Project-URL: Documentation, https://github.com/g0di/fastapi-problem-details
Project-URL: Source, https://github.com/g0di/fastapi-problem-details
Project-URL: Changelog, https://github.com/g0di/fastapi-problem-details/blob/main/README.md
Requires-Python: >=3.10
Requires-Dist: fastapi>=0.100.0
Requires-Dist: pydantic>=2.0.0
